docs/MGTron Command Description.docx
docs/MGTron Function Descriptions.docx
src/__init__.py
src/main.py
src/assets/CA logo without subtext.JPG
src/assets/CA_subheading.png
src/assets/CHANGELOG.cpy
src/assets/MGTron Command Description.pdf
src/assets/api_rs
src/assets/blueio_rs
src/assets/get_latest_version.sh
src/assets/init_cellantenna.sh
src/assets/install_mgtron.sh
src/assets/log_read
src/assets/mgtron.desktop
src/assets/mgtron.svg
src/assets/network-wireless.ico
src/assets/parse_git_log.sh
src/assets/wifi_rs
src/ble/__init__.py
src/ble/ble_data.py
src/ble/helpers.py
src/ble/scanning.py
src/db/__init__.py
src/db/channel_1.sql
src/db/channel_2.sql
src/db/channel_3.sql
src/db/channel_4.sql
src/db/channel_5.sql
src/db/channel_6.sql
src/db/channel_7.sql
src/db/channel_8.sql
src/db/helpers.py
src/db/init_db.sql
src/db/long_save.json
src/db/long_save.json.lock
src/db/mgtron_db.db
src/db/models.py
src/db/quick_save.json
src/globals/__init__.py
src/globals/helpers.py
src/gps/scanning.py
src/gui/__init__.py
src/gui/helpers.py
src/gui/interface.py
src/gui/_configs/card_1.ini
src/gui/_configs/card_2.ini
src/gui/_configs/card_3.ini
src/gui/_configs/card_4.ini
src/gui/_configs/card_5.ini
src/gui/_configs/card_6.ini
src/gui/_configs/card_7.ini
src/gui/_configs/card_8.ini
src/gui/_configs/card_config.ini
src/gui/_configs/mission_alpha.ini
src/gui/_configs/mission_bravo.ini
src/gui/_configs/mission_charlie.ini
src/gui/_configs/mission_delta.ini
src/gui/_configs/mission_echo.ini
src/gui/_configs/mission_fox.ini
src/gui/_configs/mission_golf.ini
src/gui/fonts/MesloLGS NF Bold Italic.ttf
src/gui/fonts/MesloLGS NF Italic.ttf
src/gui/fonts/MesloLGS NF Regular.ttf
src/tests/__init__.py
src/tests/test_ble.py
src/tests/test_configfiles.py
src/tests/test_dpg.py
src/tests/test_helpers.py
src/tests/test_stopdb.py
src/wifi/__init__.py
src/wifi/chasing.py
src/wifi/helpers.py
src/wifi/scanning.py
mgtron-2.27.1.dist-info/LICENSE.rst
mgtron-2.27.1.dist-info/METADATA
mgtron-2.27.1.dist-info/WHEEL
mgtron-2.27.1.dist-info/entry_points.txt
mgtron-2.27.1.dist-info/top_level.txt
mgtron-2.27.1.dist-info/RECORD
