Metadata-Version: 2.1
Name: mgtron
Version: 2.27.1
Summary: Package for MGTron GUI, a user interface for signal generation
Author-email: Christerpher Hunter <chunter@cellantenna.com>
Project-URL: Source, https://github.com/cellantenna/mg_tron
Classifier: Programming Language :: Python :: 3
Classifier: License :: Other/Proprietary License
Classifier: Operating System :: POSIX :: Linux
Requires-Python: >=3.10
License-File: LICENSE.rst
Requires-Dist: anyio ==3.7.1
Requires-Dist: autopep8 ==2.0.4
Requires-Dist: black ==23.7.0
Requires-Dist: build ==0.10.0
Requires-Dist: certifi ==2023.7.22
Requires-Dist: cfgv ==3.4.0
Requires-Dist: charset-normalizer ==3.2.0
Requires-Dist: click ==8.1.4
Requires-Dist: colorama ==0.4.6
Requires-Dist: coverage ==7.2.7
Requires-Dist: dearpygui ==1.9.1
Requires-Dist: distlib ==0.3.7
Requires-Dist: docstring-to-markdown ==0.12
Requires-Dist: EasyProcess ==1.1
Requires-Dist: entrypoint2 ==1.1
Requires-Dist: evdev ==1.6.1
Requires-Dist: fastapi ==0.99.1
Requires-Dist: filelock ==3.12.4
Requires-Dist: future ==0.18.3
Requires-Dist: gps-sentences ==0.1.6
Requires-Dist: h11 ==0.14.0
Requires-Dist: identify ==2.5.28
Requires-Dist: idna ==3.4
Requires-Dist: iniconfig ==2.0.0
Requires-Dist: iso8601 ==2.0.0
Requires-Dist: jedi ==0.18.2
Requires-Dist: jeepney ==0.8.0
Requires-Dist: mouse ==0.7.1
Requires-Dist: MouseInfo ==0.1.3
Requires-Dist: mss ==9.0.1
Requires-Dist: mypy ==1.4.1
Requires-Dist: mypy-extensions ==1.0.0
Requires-Dist: nodeenv ==1.8.0
Requires-Dist: packaging ==23.1
Requires-Dist: parso ==0.8.3
Requires-Dist: pathspec ==0.11.1
Requires-Dist: Pillow ==10.0.0
Requires-Dist: platformdirs ==3.9.1
Requires-Dist: pluggy ==1.2.0
Requires-Dist: pre-commit ==3.4.0
Requires-Dist: pycodestyle ==2.10.0
Requires-Dist: pydantic ==1.10.11
Requires-Dist: PyGetWindow ==0.0.9
Requires-Dist: PyMsgBox ==1.0.9
Requires-Dist: pynput ==1.7.6
Requires-Dist: pyperclip ==1.8.2
Requires-Dist: pyproject-hooks ==1.0.0
Requires-Dist: PyRect ==0.2.0
Requires-Dist: pyscreenshot ==3.1
Requires-Dist: PyScreeze ==0.1.29
Requires-Dist: pyserial ==3.5
Requires-Dist: pytest ==7.4.0
Requires-Dist: pytest-cov ==4.1.0
Requires-Dist: pytest-cover ==3.0.0
Requires-Dist: pytest-coverage ==0.0
Requires-Dist: python-decouple ==3.8
Requires-Dist: python-lsp-jsonrpc ==1.0.0
Requires-Dist: python-lsp-server ==1.7.4
Requires-Dist: python-xlib ==0.33
Requires-Dist: python3-xlib ==0.15
Requires-Dist: pytweening ==1.0.7
Requires-Dist: PyYAML ==6.0
Requires-Dist: requests ==2.31.0
Requires-Dist: six ==1.16.0
Requires-Dist: sniffio ==1.3.0
Requires-Dist: starlette ==0.27.0
Requires-Dist: tabulate ==0.9.0
Requires-Dist: typing-extensions ==4.7.1
Requires-Dist: ujson ==5.8.0
Requires-Dist: urllib3 ==2.0.4
Requires-Dist: uvicorn ==0.22.0
Requires-Dist: virtualenv ==20.24.5
Provides-Extra: test
Requires-Dist: pytest >=7.3.2 ; extra == 'test'
Requires-Dist: pytest-asyncio >=0.21.0 ; extra == 'test'
Requires-Dist: pytest-cov >=4.1.0 ; extra == 'test'
